{
  "_class": "shapePath",
  "booleanOperation": 0,
  "clippingMaskMode": 0,
  "do_objectID": "87867704-F648-4482-AAE0-DA157181B9FA",
  "edited": true,
  "exportOptions": {
    "_class": "exportOptions",
    "do_objectID": "E0C2D167-DD22-4656-B22E-2593C88176D5",
    "exportFormats": [
    ],
    "includedLayerIds": [
    ],
    "layerOptions": 0,
    "shouldTrim": false
  },
  "frame": {
    "_class": "rect",
    "constrainProportions": false,
    "do_objectID": "2022697F-F641-48EB-904A-43CD54D3D1B7",
    "height": 6.015565275149442,
    "width": 5.994604855629932,
    "x": 11.54441003097212,
    "y": 16.59634303760992
  },
  "hasClippingMask": false,
  "isClosed": false,
  "isFixedToViewport": false,
  "isFlippedHorizontal": false,
  "isFlippedVertical": false,
  "isLocked": false,
  "isVisible": true,
  "layerListExpandedType": 0,
  "name": "Path",
  "nameIsFixed": false,
  "pointRadiusBehaviour": 0,
  "points": [
    {
      "_class": "curvePoint",
      "cornerRadius": 0,
      "curveFrom": "{0.0049999999999998934, 0.013999999999999346}",
      "curveMode": 4,
      "curveTo": "{0.0079999999999997851, 0.010999999999999233}",
      "hasCurveFrom": true,
      "hasCurveTo": false,
      "point": "{0.0079999999999997851, 0.010999999999999233}"
    },
    {
      "_class": "curvePoint",
      "cornerRadius": 0,
      "curveFrom": "{0.0059999999999997833, 0.013999999999999346}",
      "curveMode": 4,
      "curveTo": "{0.0029999999999998916, 0.01699999999999946}",
      "hasCurveFrom": true,
      "hasCurveTo": true,
      "point": "{0, 0.020999999999999019}"
    },
    {
      "_class": "curvePoint",
      "cornerRadius": 0,
      "curveFrom": "{0.01399999999999979, 0.0030000000000001137}",
      "curveMode": 4,
      "curveTo": "{0.010999999999999899, 0.0069999999999996732}",
      "hasCurveFrom": true,
      "hasCurveTo": true,
      "point": "{0.016999999999999904, 0}"
    },
    {
      "_class": "curvePoint",
      "cornerRadius": 0,
      "curveFrom": "{0.0079999999999997851, 0.010999999999999233}",
      "curveMode": 4,
      "curveTo": "{0.010999999999999899, 0.0069999999999996732}",
      "hasCurveFrom": false,
      "hasCurveTo": true,
      "point": "{0.0079999999999997851, 0.010999999999999233}"
    }
  ],
  "resizingConstraint": 63,
  "resizingType": 0,
  "rotation": 0,
  "shouldBreakMaskChain": false,
  "style": {
    "_class": "style",
    "borders": [
      {
        "_class": "border",
        "color": {
          "_class": "color",
          "alpha": 1,
          "blue": 0.7647058823529411,
          "green": 0.5529411764705883,
          "red": 0.1215686274509804
        },
        "fillType": 0,
        "isEnabled": false,
        "position": 0,
        "thickness": 1
      }
    ],
    "do_objectID": "7425D4E2-12CA-4BB1-B7D2-483952B2D434",
    "endMarkerType": 0,
    "fills": [
      {
        "_class": "fill",
        "color": {
          "_class": "color",
          "alpha": 0.15,
          "blue": 0.9725490196078431,
          "green": 0.9725490196078431,
          "red": 0.9725490196078431
        },
        "fillType": 0,
        "isEnabled": true,
        "noiseIndex": 0,
        "noiseIntensity": 0,
        "patternFillType": 0,
        "patternTileScale": 1
      }
    ],
    "miterLimit": 10,
    "startMarkerType": 0,
    "windingRule": 1
  }
}