{
  "_class": "symbolInstance",
  "booleanOperation": -1,
  "clippingMaskMode": 0,
  "do_objectID": "1F713966-F6DC-47A5-9186-91A08A7F6B05",
  "exportOptions": {
    "_class": "exportOptions",
    "do_objectID": "245672D1-A1D7-47F4-9C22-524C16F1C2F0",
    "exportFormats": [
    ],
    "includedLayerIds": [
    ],
    "layerOptions": 0,
    "shouldTrim": false
  },
  "frame": {
    "_class": "rect",
    "constrainProportions": false,
    "do_objectID": "7F871CEF-55EB-4893-B319-827C9A9E0DD8",
    "height": 120,
    "width": 144,
    "x": 0,
    "y": 0
  },
  "hasClippingMask": false,
  "horizontalSpacing": 0,
  "isFixedToViewport": false,
  "isFlippedHorizontal": false,
  "isFlippedVertical": false,
  "isLocked": false,
  "isVisible": true,
  "layerListExpandedType": 0,
  "name": "src/annotation_bullets-full_x_2thirds",
  "nameIsFixed": false,
  "overrideValues": [
  ],
  "resizingConstraint": 63,
  "resizingType": 0,
  "rotation": 0,
  "scale": 1,
  "shouldBreakMaskChain": false,
  "style": {
    "_class": "style",
    "do_objectID": "962120BE-496C-455E-AC84-94D00561EC44",
    "endMarkerType": 0,
    "miterLimit": 10,
    "startMarkerType": 0,
    "windingRule": 1
  },
  "symbolID": "013D3182-C772-41B2-9EC4-F682F68636AD",
  "verticalSpacing": 0
}