{
  "_class": "group",
  "booleanOperation": 0,
  "clippingMaskMode": 0,
  "do_objectID": "75450EB2-F69A-44D1-A3A6-9A79517A9B09",
  "exportOptions": {
    "_class": "exportOptions",
    "do_objectID": "4E040988-1BCE-4122-B3B3-F594747C9AA1",
    "exportFormats": [
    ],
    "includedLayerIds": [
    ],
    "layerOptions": 0,
    "shouldTrim": false
  },
  "frame": {
    "_class": "rect",
    "constrainProportions": false,
    "do_objectID": "B215A0A6-9E1C-485F-9D3D-31F71FC67FB6",
    "height": 54,
    "width": 48,
    "x": 54,
    "y": 6
  },
  "groupLayout": {
    "_class": "MSImmutableFreeformGroupLayout"
  },
  "hasClickThrough": false,
  "hasClippingMask": false,
  "isFixedToViewport": false,
  "isFlippedHorizontal": false,
  "isFlippedVertical": false,
  "isLocked": false,
  "isVisible": true,
  "layerListExpandedType": 0,
  "layers": [
    {
      "class": "group",
      "id": "A78D2A09-8842-4ACC-9F06-848BA3D74360"
    }
  ],
  "name": "Cells",
  "nameIsFixed": true,
  "resizingConstraint": 63,
  "resizingType": 0,
  "rotation": 0,
  "shouldBreakMaskChain": false,
  "style": {
    "_class": "style",
    "blur": {
      "_class": "blur",
      "center": "{0.5, 0.5}",
      "do_objectID": "AED7618C-6828-4498-9EE2-8C9E652E7FAC",
      "isEnabled": false,
      "motionAngle": 0,
      "radius": 5,
      "saturation": 1,
      "type": 0
    },
    "do_objectID": "89B2CCCD-1C83-4638-A8FB-0E41D032D2B5",
    "endMarkerType": 0,
    "miterLimit": 10,
    "startMarkerType": 0,
    "windingRule": 1
  }
}