{
  "_class": "shapePath",
  "booleanOperation": 0,
  "clippingMaskMode": 0,
  "do_objectID": "F35BE424-0EF9-432C-B609-CD2B57B5E829",
  "edited": true,
  "exportOptions": {
    "_class": "exportOptions",
    "do_objectID": "6C373A6E-09C0-4A74-81D1-9A8746D23DE0",
    "exportFormats": [
    ],
    "includedLayerIds": [
    ],
    "layerOptions": 0,
    "shouldTrim": false
  },
  "frame": {
    "_class": "rect",
    "constrainProportions": false,
    "do_objectID": "BF35CF11-C6CE-4219-B57F-14A1E2933E02",
    "height": 6.015565275149452,
    "width": 5.994604855629959,
    "x": 72.05754820661403,
    "y": 16.04712192798844
  },
  "hasClippingMask": false,
  "isClosed": true,
  "isFixedToViewport": false,
  "isFlippedHorizontal": false,
  "isFlippedVertical": false,
  "isLocked": false,
  "isVisible": true,
  "layerListExpandedType": 0,
  "name": "Path",
  "nameIsFixed": false,
  "pointRadiusBehaviour": 0,
  "points": [
    {
      "_class": "curvePoint",
      "cornerRadius": 0,
      "curveFrom": "{0.00099999999999944578, 0.00099999999999944578}",
      "curveMode": 4,
      "curveTo": "{0, 0}",
      "hasCurveFrom": true,
      "hasCurveTo": false,
      "point": "{0, 0}"
    },
    {
      "_class": "curvePoint",
      "cornerRadius": 0,
      "curveFrom": "{0.00099999999999944578, 0.00099999999999944578}",
      "curveMode": 2,
      "curveTo": "{0.00099999999999944578, 0.00099999999999944578}",
      "hasCurveFrom": true,
      "hasCurveTo": true,
      "point": "{0.00099999999999944578, 0.00099999999999944578}"
    },
    {
      "_class": "curvePoint",
      "cornerRadius": 0,
      "curveFrom": "{0.00099999999999944578, 0.00099999999999944578}",
      "curveMode": 2,
      "curveTo": "{0.00099999999999944578, 0.00099999999999944578}",
      "hasCurveFrom": true,
      "hasCurveTo": true,
      "point": "{0.00099999999999944578, 0.00099999999999944578}"
    },
    {
      "_class": "curvePoint",
      "cornerRadius": 0,
      "curveFrom": "{0, 0}",
      "curveMode": 4,
      "curveTo": "{0.00099999999999944578, 0.00099999999999944578}",
      "hasCurveFrom": false,
      "hasCurveTo": true,
      "point": "{0, 0}"
    }
  ],
  "resizingConstraint": 63,
  "resizingType": 0,
  "rotation": 0,
  "shouldBreakMaskChain": false,
  "style": {
    "_class": "style",
    "borders": [
      {
        "_class": "border",
        "color": {
          "_class": "color",
          "alpha": 1,
          "blue": 0.7647058823529411,
          "green": 0.5529411764705883,
          "red": 0.1215686274509804
        },
        "fillType": 0,
        "isEnabled": false,
        "position": 1,
        "thickness": 1
      }
    ],
    "do_objectID": "1F2144F1-10A6-4629-B374-AD2B1FA87E89",
    "endMarkerType": 0,
    "fills": [
      {
        "_class": "fill",
        "color": {
          "_class": "color",
          "alpha": 0.15,
          "blue": 0.9725490196078431,
          "green": 0.9725490196078431,
          "red": 0.9725490196078431
        },
        "fillType": 0,
        "isEnabled": true,
        "noiseIndex": 0,
        "noiseIntensity": 0,
        "patternFillType": 0,
        "patternTileScale": 1
      }
    ],
    "miterLimit": 10,
    "startMarkerType": 0,
    "windingRule": 1
  }
}