{
  "_class": "shapePath",
  "booleanOperation": -1,
  "clippingMaskMode": 0,
  "do_objectID": "0F5C67EB-E10F-4B9F-9CCC-45A052653F46",
  "edited": true,
  "exportOptions": {
    "_class": "exportOptions",
    "do_objectID": "6E9EB0A3-27A2-4FB7-80B4-82B7A34D5E81",
    "exportFormats": [
    ],
    "includedLayerIds": [
    ],
    "layerOptions": 0,
    "shouldTrim": false
  },
  "frame": {
    "_class": "rect",
    "constrainProportions": false,
    "do_objectID": "579E1EE4-FEEE-400E-B8C7-52D9218FCB78",
    "height": 3.17647058823529,
    "width": 2.117647058823531,
    "x": 14.8235294117647,
    "y": 3.17647058823529
  },
  "hasClippingMask": false,
  "isClosed": true,
  "isFixedToViewport": false,
  "isFlippedHorizontal": false,
  "isFlippedVertical": false,
  "isLocked": false,
  "isVisible": true,
  "layerListExpandedType": 0,
  "name": "Path",
  "nameIsFixed": false,
  "pointRadiusBehaviour": 1,
  "points": [
    {
      "_class": "curvePoint",
      "cornerRadius": 0,
      "curveFrom": "{0.0027700831024937028, 0.97532894736842102}",
      "curveMode": 4,
      "curveTo": "{0.5235457063711918, 0.74835526315789458}",
      "hasCurveFrom": true,
      "hasCurveTo": true,
      "point": "{0, 1}"
    },
    {
      "_class": "curvePoint",
      "cornerRadius": 0,
      "curveFrom": "{0.0083102493074795336, 0.92598684210526316}",
      "curveMode": 4,
      "curveTo": "{0.0083102493074795336, 0.95065789473684215}",
      "hasCurveFrom": false,
      "hasCurveTo": true,
      "point": "{0.0083102493074795336, 0.92598684210526316}"
    },
    {
      "_class": "curvePoint",
      "cornerRadius": 0,
      "curveFrom": "{0.0083102493074795336, 0}",
      "curveMode": 1,
      "curveTo": "{0.0083102493074795336, 0}",
      "hasCurveFrom": false,
      "hasCurveTo": false,
      "point": "{0.0083102493074795336, 0}"
    },
    {
      "_class": "curvePoint",
      "cornerRadius": 0,
      "curveFrom": "{0.87811634349030387, 0.39638157894736858}",
      "curveMode": 4,
      "curveTo": "{1, 0}",
      "hasCurveFrom": true,
      "hasCurveTo": false,
      "point": "{1, 0}"
    }
  ],
  "resizingConstraint": 63,
  "resizingType": 0,
  "rotation": 0,
  "shouldBreakMaskChain": false,
  "style": {
    "_class": "style",
    "borders": [
      {
        "_class": "border",
        "color": {
          "_class": "color",
          "alpha": 1,
          "blue": 0.592,
          "green": 0.592,
          "red": 0.592
        },
        "fillType": 0,
        "isEnabled": false,
        "position": 0,
        "thickness": 1
      }
    ],
    "do_objectID": "D8803C53-DD05-464F-B59D-C741EE457ABC",
    "endMarkerType": 0,
    "fills": [
      {
        "_class": "fill",
        "color": {
          "_class": "color",
          "alpha": 1,
          "blue": 0,
          "green": 0.6823529411764706,
          "red": 0.9490196078431372
        },
        "fillType": 0,
        "isEnabled": true,
        "noiseIndex": 0,
        "noiseIntensity": 0,
        "patternFillType": 1,
        "patternTileScale": 1
      }
    ],
    "miterLimit": 10,
    "startMarkerType": 0,
    "windingRule": 0
  }
}