{
  "_class": "group",
  "booleanOperation": 0,
  "clippingMaskMode": 0,
  "do_objectID": "3B963393-160C-44CB-AA90-05834A84B508",
  "exportOptions": {
    "_class": "exportOptions",
    "do_objectID": "14262DB7-A799-4528-B721-FA02CE84ED70",
    "exportFormats": [
    ],
    "includedLayerIds": [
    ],
    "layerOptions": 0,
    "shouldTrim": false
  },
  "frame": {
    "_class": "rect",
    "constrainProportions": false,
    "do_objectID": "03206E81-4A4C-4214-BCAE-16F6069D0D71",
    "height": 48,
    "width": 132,
    "x": 6,
    "y": 6
  },
  "groupLayout": {
    "_class": "MSImmutableFreeformGroupLayout"
  },
  "hasClickThrough": false,
  "hasClippingMask": false,
  "isFixedToViewport": false,
  "isFlippedHorizontal": false,
  "isFlippedVertical": false,
  "isLocked": false,
  "isVisible": true,
  "layerListExpandedType": 0,
  "layers": [
    {
      "class": "rectangle",
      "id": "5C4F52CE-7159-4054-AC17-838913F58618"
    },
    {
      "class": "rectangle",
      "id": "5B53B69F-325E-4E0F-B97F-C7B2B4B47AF3"
    },
    {
      "class": "rectangle",
      "id": "8BF0F9FD-A74D-4212-934D-6EB08F6346B3"
    },
    {
      "class": "rectangle",
      "id": "A614B029-08CB-4975-9DE4-86566CF9999F"
    }
  ],
  "name": "Group 3",
  "nameIsFixed": false,
  "resizingConstraint": 63,
  "resizingType": 0,
  "rotation": 0,
  "shouldBreakMaskChain": false,
  "style": {
    "_class": "style",
    "do_objectID": "C8122C86-4C33-44BE-A1FB-9D5674E9445D",
    "endMarkerType": 0,
    "miterLimit": 10,
    "startMarkerType": 0,
    "windingRule": 1
  }
}