{
  "_class": "shapePath",
  "booleanOperation": 0,
  "clippingMaskMode": 0,
  "do_objectID": "3A0012AD-82F5-4A4E-A51A-5D3F16201FFB",
  "edited": true,
  "exportOptions": {
    "_class": "exportOptions",
    "do_objectID": "8C6849C3-354E-44C8-8BB6-8A255686423F",
    "exportFormats": [
    ],
    "includedLayerIds": [
    ],
    "layerOptions": 0,
    "shouldTrim": false
  },
  "frame": {
    "_class": "rect",
    "constrainProportions": false,
    "do_objectID": "9A11AB64-BEE1-4B19-9FE4-B6A5BC6E19DE",
    "height": 1,
    "width": 1,
    "x": 46.46060000000034,
    "y": 5.745499999999993
  },
  "hasClippingMask": false,
  "isClosed": true,
  "isFixedToViewport": false,
  "isFlippedHorizontal": false,
  "isFlippedVertical": false,
  "isLocked": false,
  "isVisible": true,
  "layerListExpandedType": 0,
  "name": "Path",
  "nameIsFixed": false,
  "pointRadiusBehaviour": 1,
  "points": [
    {
      "_class": "curvePoint",
      "cornerRadius": 0,
      "curveFrom": "{0.027000000000001023, 0.0010000000000047748}",
      "curveMode": 1,
      "curveTo": "{0.027000000000001023, 0.0010000000000047748}",
      "hasCurveFrom": false,
      "hasCurveTo": false,
      "point": "{0.027000000000001023, 0.0010000000000047748}"
    },
    {
      "_class": "curvePoint",
      "cornerRadius": 0,
      "curveFrom": "{0.027999999999998693, 0.0010000000000047748}",
      "curveMode": 1,
      "curveTo": "{0.027999999999998693, 0.0010000000000047748}",
      "hasCurveFrom": false,
      "hasCurveTo": false,
      "point": "{0.027999999999998693, 0.0010000000000047748}"
    },
    {
      "_class": "curvePoint",
      "cornerRadius": 0,
      "curveFrom": "{0, 0}",
      "curveMode": 1,
      "curveTo": "{0, 0}",
      "hasCurveFrom": false,
      "hasCurveTo": false,
      "point": "{0, 0}"
    }
  ],
  "resizingConstraint": 63,
  "resizingType": 0,
  "rotation": 0,
  "shouldBreakMaskChain": false,
  "style": {
    "_class": "style",
    "borders": [
      {
        "_class": "border",
        "color": {
          "_class": "color",
          "alpha": 1,
          "blue": 0.7647058823529411,
          "green": 0.5529411764705883,
          "red": 0.1215686274509804
        },
        "fillType": 0,
        "isEnabled": false,
        "position": 1,
        "thickness": 1
      }
    ],
    "do_objectID": "1A2A18BF-FEDD-4235-BA95-B46598BC4B25",
    "endMarkerType": 0,
    "fills": [
      {
        "_class": "fill",
        "color": {
          "_class": "color",
          "alpha": 0.15,
          "blue": 0.9725490196078431,
          "green": 0.9725490196078431,
          "red": 0.9725490196078431
        },
        "fillType": 0,
        "isEnabled": true,
        "noiseIndex": 0,
        "noiseIntensity": 0,
        "patternFillType": 0,
        "patternTileScale": 1
      }
    ],
    "miterLimit": 10,
    "startMarkerType": 0,
    "windingRule": 1
  }
}