{
  "_class": "rectangle",
  "booleanOperation": -1,
  "clippingMaskMode": 0,
  "do_objectID": "3E13D27F-E585-4F9E-B5F3-5132320AB045",
  "edited": false,
  "exportOptions": {
    "_class": "exportOptions",
    "do_objectID": "A8B58276-0A92-4F8E-A964-F8C15327FF2B",
    "exportFormats": [
    ],
    "includedLayerIds": [
    ],
    "layerOptions": 0,
    "shouldTrim": false
  },
  "fixedRadius": 3,
  "frame": {
    "_class": "rect",
    "constrainProportions": false,
    "do_objectID": "5AF5B5EA-0792-4631-AF51-C867BD6D414F",
    "height": 40,
    "width": 103,
    "x": 0,
    "y": -2.842170943040401e-14
  },
  "hasClippingMask": false,
  "hasConvertedToNewRoundCorners": true,
  "isClosed": true,
  "isFixedToViewport": false,
  "isFlippedHorizontal": false,
  "isFlippedVertical": false,
  "isLocked": false,
  "isVisible": true,
  "layerListExpandedType": 0,
  "name": "BG",
  "nameIsFixed": true,
  "pointRadiusBehaviour": 0,
  "points": [
    {
      "_class": "curvePoint",
      "cornerRadius": 3,
      "curveFrom": "{0, 0}",
      "curveMode": 1,
      "curveTo": "{0, 0}",
      "hasCurveFrom": false,
      "hasCurveTo": false,
      "point": "{0, 0}"
    },
    {
      "_class": "curvePoint",
      "cornerRadius": 3,
      "curveFrom": "{1, 0}",
      "curveMode": 1,
      "curveTo": "{1, 0}",
      "hasCurveFrom": false,
      "hasCurveTo": false,
      "point": "{1, 0}"
    },
    {
      "_class": "curvePoint",
      "cornerRadius": 3,
      "curveFrom": "{1, 1}",
      "curveMode": 1,
      "curveTo": "{1, 1}",
      "hasCurveFrom": false,
      "hasCurveTo": false,
      "point": "{1, 1}"
    },
    {
      "_class": "curvePoint",
      "cornerRadius": 3,
      "curveFrom": "{0, 1}",
      "curveMode": 1,
      "curveTo": "{0, 1}",
      "hasCurveFrom": false,
      "hasCurveTo": false,
      "point": "{0, 1}"
    }
  ],
  "resizingConstraint": 63,
  "resizingType": 0,
  "rotation": 0,
  "sharedStyleID": "97F73B3A-CC39-4CA7-B3FD-2BED8B02B9C0",
  "shouldBreakMaskChain": false,
  "style": {
    "_class": "style",
    "do_objectID": "223B53DF-EA02-415D-8355-3CC0CBD99F6E",
    "endMarkerType": 0,
    "fills": [
      {
        "_class": "fill",
        "color": {
          "_class": "color",
          "alpha": 0.04,
          "blue": 0.2470588235294118,
          "green": 0.2470588235294118,
          "red": 0.2470588235294118
        },
        "fillType": 0,
        "isEnabled": false,
        "noiseIndex": 0,
        "noiseIntensity": 0,
        "patternFillType": 1,
        "patternTileScale": 1
      }
    ],
    "miterLimit": 10,
    "startMarkerType": 0,
    "windingRule": 1
  }
}