{
  "_class": "group",
  "booleanOperation": 0,
  "clippingMaskMode": 0,
  "do_objectID": "2EBC1F18-8B19-4115-A100-0BEF71FAB582",
  "exportOptions": {
    "_class": "exportOptions",
    "do_objectID": "14E56147-6EEB-4F9E-8209-7F74B54BD178",
    "exportFormats": [
    ],
    "includedLayerIds": [
    ],
    "layerOptions": 0,
    "shouldTrim": false
  },
  "frame": {
    "_class": "rect",
    "constrainProportions": false,
    "do_objectID": "0B4641B5-BFC4-4669-9E3F-7239E21BDB44",
    "height": 108,
    "width": 204,
    "x": 6,
    "y": 6
  },
  "groupLayout": {
    "_class": "MSImmutableFreeformGroupLayout"
  },
  "hasClickThrough": false,
  "hasClippingMask": false,
  "isFixedToViewport": false,
  "isFlippedHorizontal": false,
  "isFlippedVertical": false,
  "isLocked": false,
  "isVisible": true,
  "layerListExpandedType": 0,
  "layers": [
    {
      "class": "shapePath",
      "id": "D339683E-BE07-4653-BAC3-6BCF8707F97D"
    },
    {
      "class": "group",
      "id": "8B5574BD-79AB-4E97-96F9-5FD6F1431177"
    }
  ],
  "name": "Mountains",
  "nameIsFixed": false,
  "resizingConstraint": 63,
  "resizingType": 0,
  "rotation": 0,
  "shouldBreakMaskChain": false,
  "style": {
    "_class": "style",
    "do_objectID": "2CD84F00-0C29-40EA-9FBF-D542C0D0B502",
    "endMarkerType": 0,
    "miterLimit": 10,
    "startMarkerType": 0,
    "windingRule": 1
  }
}