{
  "_class": "shapePath",
  "booleanOperation": 0,
  "clippingMaskMode": 0,
  "do_objectID": "1CC251F5-BA84-46E8-8779-D5DC11E5B0E2",
  "edited": true,
  "exportOptions": {
    "_class": "exportOptions",
    "exportFormats": [
    ],
    "includedLayerIds": [
    ],
    "layerOptions": 0,
    "shouldTrim": false
  },
  "frame": {
    "_class": "rect",
    "constrainProportions": false,
    "height": 6.767510934543132,
    "width": 6.743930462583656,
    "x": 40.56541612548699,
    "y": 4.26217838657495
  },
  "hasClippingMask": false,
  "isClosed": false,
  "isFixedToViewport": false,
  "isFlippedHorizontal": false,
  "isFlippedVertical": false,
  "isLocked": false,
  "isVisible": true,
  "layerListExpandedType": 0,
  "maintainScrollPosition": false,
  "name": "Path",
  "nameIsFixed": false,
  "pointRadiusBehaviour": 0,
  "points": [
    {
      "_class": "curvePoint",
      "cornerRadius": 0,
      "curveFrom": "{0.0049999999999998934, 0.16999999999999993}",
      "curveMode": 4,
      "curveTo": "{0.0030000000000001137, 0.16699999999999982}",
      "hasCurveFrom": true,
      "hasCurveTo": false,
      "point": "{0.0030000000000001137, 0.16699999999999982}"
    },
    {
      "_class": "curvePoint",
      "cornerRadius": 0,
      "curveFrom": "{0.033999999999999808, 0.17799999999999905}",
      "curveMode": 4,
      "curveTo": "{0.0080000000000000071, 0.17399999999999949}",
      "hasCurveFrom": true,
      "hasCurveTo": true,
      "point": "{0.016000000000000014, 0.17600000000000016}"
    },
    {
      "_class": "curvePoint",
      "cornerRadius": 0,
      "curveFrom": "{0.064000000000000057, 0.17799999999999905}",
      "curveMode": 4,
      "curveTo": "{0.049000000000000377, 0.17799999999999905}",
      "hasCurveFrom": false,
      "hasCurveTo": true,
      "point": "{0.064000000000000057, 0.17799999999999905}"
    },
    {
      "_class": "curvePoint",
      "cornerRadius": 0,
      "curveFrom": "{0.080000000000000071, 0.17799999999999905}",
      "curveMode": 1,
      "curveTo": "{0.080000000000000071, 0.17799999999999905}",
      "hasCurveFrom": false,
      "hasCurveTo": false,
      "point": "{0.080000000000000071, 0.17799999999999905}"
    },
    {
      "_class": "curvePoint",
      "cornerRadius": 0,
      "curveFrom": "{0.094999999999999751, 0.17799999999999905}",
      "curveMode": 4,
      "curveTo": "{0.081000000000000405, 0.17799999999999905}",
      "hasCurveFrom": true,
      "hasCurveTo": false,
      "point": "{0.081000000000000405, 0.17799999999999905}"
    },
    {
      "_class": "curvePoint",
      "cornerRadius": 0,
      "curveFrom": "{0.13600000000000012, 0.19500000000000028}",
      "curveMode": 4,
      "curveTo": "{0.10899999999999999, 0.18299999999999983}",
      "hasCurveFrom": true,
      "hasCurveTo": true,
      "point": "{0.12400000000000055, 0.18900000000000006}"
    },
    {
      "_class": "curvePoint",
      "cornerRadius": 0,
      "curveFrom": "{0.16699999999999982, 0.20100000000000051}",
      "curveMode": 4,
      "curveTo": "{0.14900000000000002, 0.19999999999999929}",
      "hasCurveFrom": true,
      "hasCurveTo": true,
      "point": "{0.16600000000000037, 0.20100000000000051}"
    },
    {
      "_class": "curvePoint",
      "cornerRadius": 0,
      "curveFrom": "{0.44000000000000039, 0.15700000000000003}",
      "curveMode": 4,
      "curveTo": "{0.34100000000000019, 0.17900000000000027}",
      "hasCurveFrom": true,
      "hasCurveTo": true,
      "point": "{0.41800000000000015, 0.14299999999999891}"
    },
    {
      "_class": "curvePoint",
      "cornerRadius": 0,
      "curveFrom": "{0.49600000000000044, 0.12199999999999989}",
      "curveMode": 2,
      "curveTo": "{0.4740000000000002, 0.1379999999999999}",
      "hasCurveFrom": true,
      "hasCurveTo": true,
      "point": "{0.48500000000000032, 0.12999999999999901}"
    },
    {
      "_class": "curvePoint",
      "cornerRadius": 0,
      "curveFrom": "{0.54000000000000004, 0.10800000000000054}",
      "curveMode": 2,
      "curveTo": "{0.50800000000000001, 0.1169999999999991}",
      "hasCurveFrom": true,
      "hasCurveTo": true,
      "point": "{0.52200000000000024, 0.11299999999999955}"
    },
    {
      "_class": "curvePoint",
      "cornerRadius": 0,
      "curveFrom": "{0.57399999999999984, 0.086000000000000298}",
      "curveMode": 3,
      "curveTo": "{0.55799999999999983, 0.10200000000000031}",
      "hasCurveFrom": true,
      "hasCurveTo": true,
      "point": "{0.5730000000000004, 0.086999999999999744}"
    },
    {
      "_class": "curvePoint",
      "cornerRadius": 0,
      "curveFrom": "{0.58199999999999985, 0.078999999999998849}",
      "curveMode": 4,
      "curveTo": "{0.57500000000000018, 0.083999999999999631}",
      "hasCurveFrom": true,
      "hasCurveTo": true,
      "point": "{0.57699999999999996, 0.083000000000000185}"
    },
    {
      "_class": "curvePoint",
      "cornerRadius": 0,
      "curveFrom": "{0.57000000000000028, 0.051000000000000156}",
      "curveMode": 4,
      "curveTo": "{0.59100000000000019, 0.071999999999999176}",
      "hasCurveFrom": true,
      "hasCurveTo": true,
      "point": "{0.58400000000000052, 0.057000000000000384}"
    },
    {
      "_class": "curvePoint",
      "cornerRadius": 0,
      "curveFrom": "{0.54300000000000015, 0.048000000000000043}",
      "curveMode": 4,
      "curveTo": "{0.54999999999999982, 0.052999999999999048}",
      "hasCurveFrom": true,
      "hasCurveTo": true,
      "point": "{0.54300000000000015, 0.051999999999999602}"
    },
    {
      "_class": "curvePoint",
      "cornerRadius": 0,
      "curveFrom": "{0.55200000000000049, 0.041000000000000369}",
      "curveMode": 4,
      "curveTo": "{0.54499999999999993, 0.045999999999999375}",
      "hasCurveFrom": true,
      "hasCurveTo": true,
      "point": "{0.54999999999999982, 0.042999999999999261}"
    },
    {
      "_class": "curvePoint",
      "cornerRadius": 0,
      "curveFrom": "{0.55400000000000027, 0.020999999999999019}",
      "curveMode": 4,
      "curveTo": "{0.5550000000000006, 0.038999999999999702}",
      "hasCurveFrom": true,
      "hasCurveTo": true,
      "point": "{0.55799999999999983, 0.030999999999998806}"
    },
    {
      "_class": "curvePoint",
      "cornerRadius": 0,
      "curveFrom": "{0.53500000000000014, 0.019999999999999574}",
      "curveMode": 2,
      "curveTo": "{0.54499999999999993, 0.019999999999999574}",
      "hasCurveFrom": true,
      "hasCurveTo": true,
      "point": "{0.53900000000000059, 0.019999999999999574}"
    },
    {
      "_class": "curvePoint",
      "cornerRadius": 0,
      "curveFrom": "{0.5259999999999998, 0.01699999999999946}",
      "curveMode": 2,
      "curveTo": "{0.53200000000000003, 0.019999999999999574}",
      "hasCurveFrom": true,
      "hasCurveTo": true,
      "point": "{0.52800000000000047, 0.017999999999998906}"
    },
    {
      "_class": "curvePoint",
      "cornerRadius": 0,
      "curveFrom": "{0.52200000000000024, 0.0079999999999991189}",
      "curveMode": 4,
      "curveTo": "{0.52500000000000036, 0.016000000000000014}",
      "hasCurveFrom": true,
      "hasCurveTo": true,
      "point": "{0.52400000000000002, 0.012000000000000455}"
    },
    {
      "_class": "curvePoint",
      "cornerRadius": 0,
      "curveFrom": "{0.50600000000000023, 0}",
      "curveMode": 4,
      "curveTo": "{0.51900000000000013, 0.0030000000000001137}",
      "hasCurveFrom": true,
      "hasCurveTo": true,
      "point": "{0.50800000000000001, 0.00099999999999944578}"
    },
    {
      "_class": "curvePoint",
      "cornerRadius": 0,
      "curveFrom": "{0.5, 0}",
      "curveMode": 4,
      "curveTo": "{0.50300000000000011, 0}",
      "hasCurveFrom": false,
      "hasCurveTo": true,
      "point": "{0.5, 0}"
    },
    {
      "_class": "curvePoint",
      "cornerRadius": 0,
      "curveFrom": "{0.48800000000000043, 0.0019999999999988916}",
      "curveMode": 4,
      "curveTo": "{0.49899999999999967, 0}",
      "hasCurveFrom": true,
      "hasCurveTo": false,
      "point": "{0.49899999999999967, 0}"
    },
    {
      "_class": "curvePoint",
      "cornerRadius": 0,
      "curveFrom": "{0.46700000000000053, 0.017999999999998906}",
      "curveMode": 4,
      "curveTo": "{0.48000000000000043, 0.0079999999999991189}",
      "hasCurveFrom": true,
      "hasCurveTo": true,
      "point": "{0.47299999999999986, 0.012999999999999901}"
    },
    {
      "_class": "curvePoint",
      "cornerRadius": 0,
      "curveFrom": "{0.44899999999999984, 0.025999999999999801}",
      "curveMode": 4,
      "curveTo": "{0.46199999999999974, 0.022000000000000242}",
      "hasCurveFrom": true,
      "hasCurveTo": true,
      "point": "{0.45500000000000007, 0.023999999999999133}"
    },
    {
      "_class": "curvePoint",
      "cornerRadius": 0,
      "curveFrom": "{0.42999999999999972, 0.025999999999999801}",
      "curveMode": 2,
      "curveTo": "{0.4430000000000005, 0.025999999999999801}",
      "hasCurveFrom": true,
      "hasCurveTo": true,
      "point": "{0.43599999999999994, 0.025999999999999801}"
    },
    {
      "_class": "curvePoint",
      "cornerRadius": 0,
      "curveFrom": "{0.41000000000000014, 0.025999999999999801}",
      "curveMode": 4,
      "curveTo": "{0.42199999999999971, 0.025000000000000355}",
      "hasCurveFrom": true,
      "hasCurveTo": true,
      "point": "{0.41600000000000037, 0.025999999999999801}"
    },
    {
      "_class": "curvePoint",
      "cornerRadius": 0,
      "curveFrom": "{0.39900000000000002, 0.022000000000000242}",
      "curveMode": 4,
      "curveTo": "{0.40800000000000036, 0.025000000000000355}",
      "hasCurveFrom": true,
      "hasCurveTo": true,
      "point": "{0.40300000000000047, 0.023999999999999133}"
    },
    {
      "_class": "curvePoint",
      "cornerRadius": 0,
      "curveFrom": "{0.39200000000000035, 0.026999999999999247}",
      "curveMode": 4,
      "curveTo": "{0.39599999999999991, 0.025999999999999801}",
      "hasCurveFrom": true,
      "hasCurveTo": true,
      "point": "{0.39200000000000035, 0.026999999999999247}"
    },
    {
      "_class": "curvePoint",
      "cornerRadius": 0,
      "curveFrom": "{0.38999999999999968, 0.026999999999999247}",
      "curveMode": 2,
      "curveTo": "{0.39100000000000001, 0.026999999999999247}",
      "hasCurveFrom": true,
      "hasCurveTo": true,
      "point": "{0.39100000000000001, 0.026999999999999247}"
    },
    {
      "_class": "curvePoint",
      "cornerRadius": 0,
      "curveFrom": "{0.38300000000000001, 0.029999999999999361}",
      "curveMode": 4,
      "curveTo": "{0.38900000000000023, 0.028000000000000469}",
      "hasCurveFrom": true,
      "hasCurveTo": true,
      "point": "{0.38900000000000023, 0.028000000000000469}"
    },
    {
      "_class": "curvePoint",
      "cornerRadius": 0,
      "curveFrom": "{0.37100000000000044, 0.035000000000000142}",
      "curveMode": 4,
      "curveTo": "{0.37600000000000033, 0.028999999999999915}",
      "hasCurveFrom": true,
      "hasCurveTo": true,
      "point": "{0.37300000000000022, 0.032999999999999474}"
    },
    {
      "_class": "curvePoint",
      "cornerRadius": 0,
      "curveFrom": "{0.35200000000000031, 0.020999999999999019}",
      "curveMode": 4,
      "curveTo": "{0.36500000000000021, 0.038000000000000256}",
      "hasCurveFrom": true,
      "hasCurveTo": true,
      "point": "{0.36600000000000055, 0.038000000000000256}"
    },
    {
      "_class": "curvePoint",
      "cornerRadius": 0,
      "curveFrom": "{0.31599999999999984, 0.025999999999999801}",
      "curveMode": 4,
      "curveTo": "{0.35000000000000053, 0.019999999999999574}",
      "hasCurveFrom": true,
      "hasCurveTo": true,
      "point": "{0.33000000000000007, 0.023999999999999133}"
    },
    {
      "_class": "curvePoint",
      "cornerRadius": 0,
      "curveFrom": "{0.29800000000000004, 0.042999999999999261}",
      "curveMode": 4,
      "curveTo": "{0.30600000000000005, 0.035999999999999588}",
      "hasCurveFrom": true,
      "hasCurveTo": true,
      "point": "{0.29800000000000004, 0.042999999999999261}"
    },
    {
      "_class": "curvePoint",
      "cornerRadius": 0,
      "curveFrom": "{0.29699999999999971, 0.039999999999999147}",
      "curveMode": 4,
      "curveTo": "{0.29800000000000004, 0.041999999999999815}",
      "hasCurveFrom": true,
      "hasCurveTo": true,
      "point": "{0.29800000000000004, 0.041999999999999815}"
    },
    {
      "_class": "curvePoint",
      "cornerRadius": 0,
      "curveFrom": "{0.29900000000000038, 0.030999999999998806}",
      "curveMode": 4,
      "curveTo": "{0.29800000000000004, 0.035000000000000142}",
      "hasCurveFrom": true,
      "hasCurveTo": true,
      "point": "{0.29800000000000004, 0.032000000000000028}"
    },
    {
      "_class": "curvePoint",
      "cornerRadius": 0,
      "curveFrom": "{0.28600000000000048, 0.013999999999999346}",
      "curveMode": 4,
      "curveTo": "{0.29900000000000038, 0.025000000000000355}",
      "hasCurveFrom": true,
      "hasCurveTo": true,
      "point": "{0.29699999999999971, 0.023999999999999133}"
    },
    {
      "_class": "curvePoint",
      "cornerRadius": 0,
      "curveFrom": "{0.26799999999999979, 0.03399999999999892}",
      "curveMode": 4,
      "curveTo": "{0.27800000000000047, 0.025999999999999801}",
      "hasCurveFrom": true,
      "hasCurveTo": true,
      "point": "{0.27000000000000046, 0.032999999999999474}"
    },
    {
      "_class": "curvePoint",
      "cornerRadius": 0,
      "curveFrom": "{0.25999999999999979, 0.038000000000000256}",
      "curveMode": 2,
      "curveTo": "{0.26499999999999968, 0.032999999999999474}",
      "hasCurveFrom": true,
      "hasCurveTo": true,
      "point": "{0.2629999999999999, 0.035000000000000142}"
    },
    {
      "_class": "curvePoint",
      "cornerRadius": 0,
      "curveFrom": "{0.24800000000000022, 0.044999999999999929}",
      "curveMode": 4,
      "curveTo": "{0.25600000000000023, 0.035000000000000142}",
      "hasCurveFrom": true,
      "hasCurveTo": true,
      "point": "{0.25400000000000045, 0.038000000000000256}"
    },
    {
      "_class": "curvePoint",
      "cornerRadius": 0,
      "curveFrom": "{0.2240000000000002, 0.057999999999999829}",
      "curveMode": 4,
      "curveTo": "{0.24199999999999999, 0.051999999999999602}",
      "hasCurveFrom": true,
      "hasCurveTo": true,
      "point": "{0.23500000000000032, 0.05400000000000027}"
    },
    {
      "_class": "curvePoint",
      "cornerRadius": 0,
      "curveFrom": "{0.19700000000000006, 0.064999999999999503}",
      "curveMode": 4,
      "curveTo": "{0.21400000000000041, 0.060999999999999943}",
      "hasCurveFrom": true,
      "hasCurveTo": true,
      "point": "{0.20300000000000029, 0.064000000000000057}"
    },
    {
      "_class": "curvePoint",
      "cornerRadius": 0,
      "curveFrom": "{0.19000000000000039, 0.061999999999999389}",
      "curveMode": 4,
      "curveTo": "{0.19200000000000017, 0.067000000000000171}",
      "hasCurveFrom": true,
      "hasCurveTo": true,
      "point": "{0.18700000000000028, 0.067999999999999616}"
    },
    {
      "_class": "curvePoint",
      "cornerRadius": 0,
      "curveFrom": "{0.21499999999999986, 0.049999999999998934}",
      "curveMode": 4,
      "curveTo": "{0.19599999999999973, 0.058999999999999275}",
      "hasCurveFrom": true,
      "hasCurveTo": true,
      "point": "{0.20399999999999974, 0.054999999999999716}"
    },
    {
      "_class": "curvePoint",
      "cornerRadius": 0,
      "curveFrom": "{0.22900000000000009, 0.0090000000000003411}",
      "curveMode": 2,
      "curveTo": "{0.22700000000000031, 0.044000000000000483}",
      "hasCurveFrom": true,
      "hasCurveTo": true,
      "point": "{0.22799999999999976, 0.026999999999999247}"
    },
    {
      "_class": "curvePoint",
      "cornerRadius": 0,
      "curveFrom": "{0.19599999999999973, 0.0069999999999996732}",
      "curveMode": 4,
      "curveTo": "{0.21300000000000008, 0.0079999999999991189}",
      "hasCurveFrom": true,
      "hasCurveTo": true,
      "point": "{0.20199999999999996, 0.0069999999999996732}"
    },
    {
      "_class": "curvePoint",
      "cornerRadius": 0,
      "curveFrom": "{0.16500000000000004, 0.0079999999999991189}",
      "curveMode": 4,
      "curveTo": "{0.18900000000000006, 0.0069999999999996732}",
      "hasCurveFrom": true,
      "hasCurveTo": true,
      "point": "{0.18100000000000005, 0.0039999999999995595}"
    },
    {
      "_class": "curvePoint",
      "cornerRadius": 0,
      "curveFrom": "{0.15599999999999969, 0.028999999999999915}",
      "curveMode": 4,
      "curveTo": "{0.15800000000000036, 0.020999999999999019}",
      "hasCurveFrom": true,
      "hasCurveTo": true,
      "point": "{0.15599999999999969, 0.028000000000000469}"
    },
    {
      "_class": "curvePoint",
      "cornerRadius": 0,
      "curveFrom": "{0.1509999999999998, 0.028999999999999915}",
      "curveMode": 2,
      "curveTo": "{0.15500000000000025, 0.028999999999999915}",
      "hasCurveFrom": true,
      "hasCurveTo": true,
      "point": "{0.15399999999999991, 0.028999999999999915}"
    },
    {
      "_class": "curvePoint",
      "cornerRadius": 0,
      "curveFrom": "{0.14100000000000001, 0.022000000000000242}",
      "curveMode": 4,
      "curveTo": "{0.14900000000000002, 0.026999999999999247}",
      "hasCurveFrom": true,
      "hasCurveTo": true,
      "point": "{0.14500000000000046, 0.023999999999999133}"
    },
    {
      "_class": "curvePoint",
      "cornerRadius": 0,
      "curveFrom": "{0.12600000000000033, 0.01699999999999946}",
      "curveMode": 4,
      "curveTo": "{0.13600000000000012, 0.017999999999998906}",
      "hasCurveFrom": true,
      "hasCurveTo": true,
      "point": "{0.13100000000000023, 0.017999999999998906}"
    },
    {
      "_class": "curvePoint",
      "cornerRadius": 0,
      "curveFrom": "{0.11000000000000032, 0.023999999999999133}",
      "curveMode": 4,
      "curveTo": "{0.12300000000000022, 0.019000000000000128}",
      "hasCurveFrom": true,
      "hasCurveTo": true,
      "point": "{0.11699999999999999, 0.022000000000000242}"
    },
    {
      "_class": "curvePoint",
      "cornerRadius": 0,
      "curveFrom": "{0.10000000000000053, 0.038999999999999702}",
      "curveMode": 4,
      "curveTo": "{0.10599999999999987, 0.029999999999999361}",
      "hasCurveFrom": true,
      "hasCurveTo": true,
      "point": "{0.10299999999999976, 0.035000000000000142}"
    },
    {
      "_class": "curvePoint",
      "cornerRadius": 0,
      "curveFrom": "{0.083000000000000185, 0.048999999999999488}",
      "curveMode": 4,
      "curveTo": "{0.097000000000000419, 0.042999999999999261}",
      "hasCurveFrom": true,
      "hasCurveTo": true,
      "point": "{0.094000000000000306, 0.044000000000000483}"
    },
    {
      "_class": "curvePoint",
      "cornerRadius": 0,
      "curveFrom": "{0.046999999999999709, 0.052999999999999048}",
      "curveMode": 4,
      "curveTo": "{0.067000000000000171, 0.042999999999999261}",
      "hasCurveFrom": true,
      "hasCurveTo": true,
      "point": "{0.049999999999999822, 0.051000000000000156}"
    },
    {
      "_class": "curvePoint",
      "cornerRadius": 0,
      "curveFrom": "{0.033999999999999808, 0.064000000000000057}",
      "curveMode": 4,
      "curveTo": "{0.041000000000000369, 0.054999999999999716}",
      "hasCurveFrom": true,
      "hasCurveTo": true,
      "point": "{0.036000000000000476, 0.060000000000000497}"
    },
    {
      "_class": "curvePoint",
      "cornerRadius": 0,
      "curveFrom": "{0.033000000000000362, 0.07099999999999973}",
      "curveMode": 2,
      "curveTo": "{0.033000000000000362, 0.067000000000000171}",
      "hasCurveFrom": true,
      "hasCurveTo": true,
      "point": "{0.033000000000000362, 0.068999999999999062}"
    },
    {
      "_class": "curvePoint",
      "cornerRadius": 0,
      "curveFrom": "{0.05400000000000027, 0.084999999999999076}",
      "curveMode": 4,
      "curveTo": "{0.033999999999999808, 0.073000000000000398}",
      "hasCurveFrom": true,
      "hasCurveTo": true,
      "point": "{0.035000000000000142, 0.073999999999999844}"
    },
    {
      "_class": "curvePoint",
      "cornerRadius": 0,
      "curveFrom": "{0.10800000000000054, 0.076000000000000512}",
      "curveMode": 4,
      "curveTo": "{0.073000000000000398, 0.081999999999998963}",
      "hasCurveFrom": true,
      "hasCurveTo": true,
      "point": "{0.094999999999999751, 0.078999999999998849}"
    },
    {
      "_class": "curvePoint",
      "cornerRadius": 0,
      "curveFrom": "{0.12999999999999989, 0.084999999999999076}",
      "curveMode": 4,
      "curveTo": "{0.11800000000000033, 0.074999999999999289}",
      "hasCurveFrom": true,
      "hasCurveTo": true,
      "point": "{0.13400000000000034, 0.077999999999999403}"
    },
    {
      "_class": "curvePoint",
      "cornerRadius": 0,
      "curveFrom": "{0.01499999999999968, 0.096999999999999531}",
      "curveMode": 4,
      "curveTo": "{0.11800000000000033, 0.086000000000000298}",
      "hasCurveFrom": true,
      "hasCurveTo": true,
      "point": "{0.049999999999999822, 0.092999999999999972}"
    },
    {
      "_class": "curvePoint",
      "cornerRadius": 0,
      "curveFrom": "{0, 0.12100000000000044}",
      "curveMode": 3,
      "curveTo": "{0, 0.10500000000000043}",
      "hasCurveFrom": true,
      "hasCurveTo": true,
      "point": "{0, 0.11899999999999977}"
    },
    {
      "_class": "curvePoint",
      "cornerRadius": 0,
      "curveFrom": "{0.014000000000000234, 0.12899999999999956}",
      "curveMode": 4,
      "curveTo": "{0.001000000000000334, 0.12299999999999933}",
      "hasCurveFrom": true,
      "hasCurveTo": true,
      "point": "{0.0030000000000001137, 0.12299999999999933}"
    },
    {
      "_class": "curvePoint",
      "cornerRadius": 0,
      "curveFrom": "{0.046000000000000263, 0.12299999999999933}",
      "curveMode": 2,
      "curveTo": "{0.025999999999999801, 0.12699999999999889}",
      "hasCurveFrom": true,
      "hasCurveTo": true,
      "point": "{0.036000000000000476, 0.125}"
    },
    {
      "_class": "curvePoint",
      "cornerRadius": 0,
      "curveFrom": "{0.064000000000000057, 0.11999999999999922}",
      "curveMode": 4,
      "curveTo": "{0.060000000000000497, 0.12199999999999989}",
      "hasCurveFrom": false,
      "hasCurveTo": true,
      "point": "{0.064000000000000057, 0.11999999999999922}"
    },
    {
      "_class": "curvePoint",
      "cornerRadius": 0,
      "curveFrom": "{0.07099999999999973, 0.11999999999999922}",
      "curveMode": 1,
      "curveTo": "{0.07099999999999973, 0.11999999999999922}",
      "hasCurveFrom": false,
      "hasCurveTo": false,
      "point": "{0.07099999999999973, 0.11999999999999922}"
    },
    {
      "_class": "curvePoint",
      "cornerRadius": 0,
      "curveFrom": "{0.07099999999999973, 0.11999999999999922}",
      "curveMode": 4,
      "curveTo": "{0.07099999999999973, 0.11999999999999922}",
      "hasCurveFrom": true,
      "hasCurveTo": false,
      "point": "{0.07099999999999973, 0.11999999999999922}"
    },
    {
      "_class": "curvePoint",
      "cornerRadius": 0,
      "curveFrom": "{0.07099999999999973, 0.11999999999999922}",
      "curveMode": 4,
      "curveTo": "{0.07099999999999973, 0.11999999999999922}",
      "hasCurveFrom": false,
      "hasCurveTo": true,
      "point": "{0.07099999999999973, 0.11999999999999922}"
    },
    {
      "_class": "curvePoint",
      "cornerRadius": 0,
      "curveFrom": "{0.062999999999999723, 0.12800000000000011}",
      "curveMode": 4,
      "curveTo": "{0.062999999999999723, 0.12599999999999945}",
      "hasCurveFrom": true,
      "hasCurveTo": false,
      "point": "{0.062999999999999723, 0.12599999999999945}"
    },
    {
      "_class": "curvePoint",
      "cornerRadius": 0,
      "curveFrom": "{0.065000000000000391, 0.13299999999999912}",
      "curveMode": 4,
      "curveTo": "{0.062999999999999723, 0.12999999999999901}",
      "hasCurveFrom": true,
      "hasCurveTo": true,
      "point": "{0.064000000000000057, 0.13199999999999967}"
    },
    {
      "_class": "curvePoint",
      "cornerRadius": 0,
      "curveFrom": "{0.062999999999999723, 0.13599999999999923}",
      "curveMode": 4,
      "curveTo": "{0.065999999999999837, 0.13400000000000034}",
      "hasCurveFrom": true,
      "hasCurveTo": true,
      "point": "{0.068000000000000504, 0.13499999999999979}"
    },
    {
      "_class": "curvePoint",
      "cornerRadius": 0,
      "curveFrom": "{0.035000000000000142, 0.13899999999999935}",
      "curveMode": 4,
      "curveTo": "{0.057999999999999829, 0.13599999999999923}",
      "hasCurveFrom": true,
      "hasCurveTo": true,
      "point": "{0.052999999999999936, 0.13700000000000045}"
    },
    {
      "_class": "curvePoint",
      "cornerRadius": 0,
      "curveFrom": "{0.0030000000000001137, 0.16699999999999982}",
      "curveMode": 4,
      "curveTo": "{0.01499999999999968, 0.14199999999999946}",
      "hasCurveFrom": false,
      "hasCurveTo": true,
      "point": "{0.0030000000000001137, 0.16699999999999982}"
    }
  ],
  "resizingConstraint": 63,
  "resizingType": 0,
  "rotation": 0,
  "shouldBreakMaskChain": false,
  "style": {
    "_class": "style",
    "blur": {
      "_class": "blur",
      "center": "{0.5, 0.5}",
      "isEnabled": false,
      "motionAngle": 0,
      "radius": 10,
      "saturation": 1,
      "type": 0
    },
    "borderOptions": {
      "_class": "borderOptions",
      "dashPattern": [
      ],
      "isEnabled": true,
      "lineCapStyle": 0,
      "lineJoinStyle": 0
    },
    "borders": [
      {
        "_class": "border",
        "color": {
          "_class": "color",
          "alpha": 1,
          "blue": 0.7647058823529411,
          "green": 0.5529411764705883,
          "red": 0.1215686274509804
        },
        "contextSettings": {
          "_class": "graphicsContextSettings",
          "blendMode": 0,
          "opacity": 1
        },
        "fillType": 0,
        "gradient": {
          "_class": "gradient",
          "elipseLength": 0,
          "from": "{0.5, 0}",
          "gradientType": 0,
          "stops": [
            {
              "_class": "gradientStop",
              "color": {
                "_class": "color",
                "alpha": 1,
                "blue": 1,
                "green": 1,
                "red": 1
              },
              "position": 0
            },
            {
              "_class": "gradientStop",
              "color": {
                "_class": "color",
                "alpha": 1,
                "blue": 0,
                "green": 0,
                "red": 0
              },
              "position": 1
            }
          ],
          "to": "{0.5, 1}"
        },
        "isEnabled": false,
        "position": 0,
        "thickness": 1
      }
    ],
    "colorControls": {
      "_class": "colorControls",
      "brightness": 0,
      "contrast": 1,
      "hue": 0,
      "isEnabled": false,
      "saturation": 1
    },
    "contextSettings": {
      "_class": "graphicsContextSettings",
      "blendMode": 0,
      "opacity": 1
    },
    "do_objectID": "CEA11B8A-AE6D-4CAB-A7C8-B4664B42B4B2",
    "endMarkerType": 0,
    "fills": [
      {
        "_class": "fill",
        "color": {
          "_class": "color",
          "alpha": 0.15,
          "blue": 0.9725490196078431,
          "green": 0.9725490196078431,
          "red": 0.9725490196078431
        },
        "contextSettings": {
          "_class": "graphicsContextSettings",
          "blendMode": 0,
          "opacity": 1
        },
        "fillType": 0,
        "gradient": {
          "_class": "gradient",
          "elipseLength": 0,
          "from": "{0.5, 0}",
          "gradientType": 0,
          "stops": [
            {
              "_class": "gradientStop",
              "color": {
                "_class": "color",
                "alpha": 1,
                "blue": 1,
                "green": 1,
                "red": 1
              },
              "position": 0
            },
            {
              "_class": "gradientStop",
              "color": {
                "_class": "color",
                "alpha": 1,
                "blue": 0,
                "green": 0,
                "red": 0
              },
              "position": 1
            }
          ],
          "to": "{0.5, 1}"
        },
        "isEnabled": true,
        "noiseIndex": 0,
        "noiseIntensity": 0,
        "patternFillType": 0,
        "patternTileScale": 1
      }
    ],
    "innerShadows": [
    ],
    "miterLimit": 10,
    "shadows": [
    ],
    "startMarkerType": 0,
    "windingRule": 1
  }
}