{
  "_class": "group",
  "booleanOperation": 0,
  "clippingMaskMode": 0,
  "do_objectID": "305B4909-3A85-4E5B-9F7D-BFE62AF00431",
  "exportOptions": {
    "_class": "exportOptions",
    "do_objectID": "A90E6255-C8B8-463A-8A34-4A34B9C8B78D",
    "exportFormats": [
    ],
    "includedLayerIds": [
    ],
    "layerOptions": 0,
    "shouldTrim": false
  },
  "frame": {
    "_class": "rect",
    "constrainProportions": false,
    "do_objectID": "73F3ED02-9D47-4F96-A7DA-B8595585542B",
    "height": 4,
    "width": 4,
    "x": 48.66666666666666,
    "y": 11
  },
  "groupLayout": {
    "_class": "MSImmutableFreeformGroupLayout"
  },
  "hasClickThrough": false,
  "hasClippingMask": false,
  "isFixedToViewport": false,
  "isFlippedHorizontal": false,
  "isFlippedVertical": false,
  "isLocked": false,
  "isVisible": true,
  "layerListExpandedType": 0,
  "layers": [
    {
      "class": "shapeGroup",
      "id": "2ADD251A-604B-4D52-B633-A40480C486E1"
    }
  ],
  "name": "Moon Icon",
  "nameIsFixed": true,
  "resizingConstraint": 63,
  "resizingType": 0,
  "rotation": 0,
  "shouldBreakMaskChain": false,
  "style": {
    "_class": "style",
    "blur": {
      "_class": "blur",
      "center": "{0.5, 0.5}",
      "do_objectID": "0CCCDB9C-5754-45E2-B509-1F8BEF11691B",
      "isEnabled": false,
      "motionAngle": 0,
      "radius": 3.333333333333333,
      "saturation": 1,
      "type": 0
    },
    "do_objectID": "0694776B-B2AD-427C-88ED-DC62B9578218",
    "endMarkerType": 0,
    "miterLimit": 10,
    "startMarkerType": 0,
    "windingRule": 1
  }
}